 {
        "payPwdStatus": 0,
        "idCardName": null,
        "cardName": "陈棒棒",
        "idCard": null,
        "openId": "ozxTn1dTQvLaHRVaPTEOlTe8UNYs",
        "annualfee": 360.0,
        "referee": "81c3725549204a118b59ef351039c2c0",
        "type": 1,
        "openType": 3,
        "balance": 0.0,
        "payPwd": null,
        "id": "3d6125bbc87a4a4e9e13bb6d227ed229",
        "isEnt": 2,
        "vipStartTime": "2018-11-21 10:53:28",
        "updateTime": "2019-01-12 21:35:27",
        "portrait": "http://cdn.hlymp.com/622095b4-4134-139a-145c-f9e0a7d17ecb",
        "token": "5c87deedbd464d4a9f75a980c326a04f",
        "vipEndTime": "2019-11-21 23:59:59",
        "phone": "13400645310",
        "createTime": "2018-10-23 15:34:13",
        "name": null,
        "expiryTime": 299,
        "position": "",
        "pwd": "21218CCA77804D2BA1922C33E0151105",
        "status": 1
    }